README.txt
setup.py
bin/structurx-run.py
src/StructuRX.egg-info/PKG-INFO
src/StructuRX.egg-info/SOURCES.txt
src/StructuRX.egg-info/dependency_links.txt
src/StructuRX.egg-info/requires.txt
src/StructuRX.egg-info/top_level.txt
src/StructuRX.egg-info/zip-safe
src/structurx/__init__.py
src/structurx/config.py
src/structurx/ctakes.py
src/structurx/deprules.py
src/structurx/evaluate.py
src/structurx/numbers.py
src/structurx/rxparse.py
src/structurx/tests.py