Metadata-Version: 1.0
Name: StructuRX
Version: 0.2
Summary: Interpret medication prescriptions into a structured format using dependency parses or third-party drug NER pipeline
Home-page: http://opennicta.com/home/structurx
Author: Andrew MacKinlay
Author-email: andrew.mackinlay@nicta.com.au
License: Apache 2.0
Download-URL: https://bitbucket.org/nicta_biomed/structurx/downloads
Platform: UNKNOWN
